MANIFEST.in
README.md
setup.py
portinfo/__init__.py
portinfo/cli.py
portinfo/portinfo.csv
portinfo/portinfo.py
portinfo.egg-info/PKG-INFO
portinfo.egg-info/SOURCES.txt
portinfo.egg-info/dependency_links.txt
portinfo.egg-info/entry_points.txt
portinfo.egg-info/not-zip-safe
portinfo.egg-info/top_level.txt