Metadata-Version: 1.0
Name: portinfo
Version: 0.1.0
Summary: Search standard services by its port.
Home-page: http://github.com/nunodio/portinfo
Author: Nuno Dionisio
Author-email: nunodio@outlook.com
License: MIT
Platform: UNKNOWN
